plainbook/__init__.py
plainbook/gemini.py
plainbook/main.py
plainbook/plainbook.py
plainbook/css/font-awesome.css
plainbook/css/font-awesome.min.css
plainbook/css/main.css
plainbook/css/prism.min.css
plainbook/fonts/FontAwesome.otf
plainbook/fonts/fontawesome-webfont.eot
plainbook/fonts/fontawesome-webfont.svg
plainbook/fonts/fontawesome-webfont.ttf
plainbook/fonts/fontawesome-webfont.woff
plainbook/fonts/fontawesome-webfont.woff2
plainbook/js/AppNavbar.js
plainbook/js/CellInsertionZone.js
plainbook/js/CodeCell.js
plainbook/js/ExplanationEditor.js
plainbook/js/InfoModal.js
plainbook/js/MarkdownCell.js
plainbook/js/NotebookCell.js
plainbook/js/OutputRenderer.js
plainbook/js/SettingsModal.js
plainbook/js/ValidationCell.js
plainbook/js/markdown-it.min.js
plainbook/js/nb.js
plainbook/js/prism-python.min.js
plainbook/js/prism.min.js
plainbook/js/vue.esm-browser.js
plainbook/views/index.html
plainbook-0.0.9.dist-info/licenses/LICENSE.md
plainbook-0.0.9.dist-info/METADATA
plainbook-0.0.9.dist-info/WHEEL
plainbook-0.0.9.dist-info/entry_points.txt
plainbook-0.0.9.dist-info/top_level.txt
plainbook-0.0.9.dist-info/RECORD
